sansa/__init__.py
sansa/model.py
sansa/core/__init__.py
sansa/core/factorizers.py
sansa/core/inverters.py
sansa/core/_ops/__init__.py
sansa/core/_ops/_factor_ops.py
sansa/core/_ops/_inverse_ops.py
sansa/utils/__init__.py
sansa/utils/matmat.py
sansa/utils/norms.py
sansa/utils/scaling.py
sansa/utils/sparsify.py
sansa/utils/topk.py
sansa-1.1.0.dist-info/LICENSE
sansa-1.1.0.dist-info/METADATA
sansa-1.1.0.dist-info/NOTICE
sansa-1.1.0.dist-info/WHEEL
sansa-1.1.0.dist-info/top_level.txt
sansa-1.1.0.dist-info/RECORD
