Metadata-Version: 2.1
Name: sansa
Version: 1.1.0
Summary: Scalable collaborative filtering model based on sparse approximate inverse
Author-email: Martin Spisak <masp430@gmail.com>, Radek Bartyzal <radek.bartyzal@glami.cz>, Antonin Hoskovec <antonin.hoskovec@glami.cz>, Ladislav Peska <ladislav.peska@matfyz.cuni.cz>, Miroslav Tuma <miroslav.tuma@mff.cuni.cz>
Maintainer-email: Martin Spisak <masp430@gmail.com>
License: Apache License
Project-URL: Homepage, https://github.com/glami/sansa
Project-URL: Repository, https://github.com/glami/sansa.git
Project-URL: Issues, https://github.com/glami/sansa/issues
Keywords: recommendation,collaborative filtering,sparse matrix,sparse approximate inverse
Classifier: Development Status :: 4 - Beta
Classifier: Programming Language :: Python :: 3
Classifier: Programming Language :: Python :: 3.10
Classifier: Programming Language :: Python :: 3.11
Classifier: Programming Language :: Python :: 3.12
Classifier: Operating System :: OS Independent
Classifier: License :: OSI Approved :: Apache Software License
Classifier: Intended Audience :: Developers
Classifier: Intended Audience :: Science/Research
Classifier: Topic :: Internet :: WWW/HTTP :: Indexing/Search
Classifier: Topic :: Scientific/Engineering
Classifier: Topic :: Scientific/Engineering :: Artificial Intelligence
Classifier: Topic :: Scientific/Engineering :: Mathematics
Requires-Python: >=3.10
License-File: LICENSE
License-File: NOTICE
Requires-Dist: numba >=0.57.0
Requires-Dist: numpy >=1.22.3
Requires-Dist: scikit-sparse >=0.4.8
Requires-Dist: scipy >=1.7.3
Provides-Extra: demo
Requires-Dist: jupyter ; extra == 'demo'
Requires-Dist: matplotlib ; extra == 'demo'
Requires-Dist: pandas ; extra == 'demo'
Requires-Dist: pyarrow ; extra == 'demo'
Requires-Dist: ipyplot ; extra == 'demo'
Requires-Dist: scikit-learn ; extra == 'demo'
Provides-Extra: dev
Requires-Dist: black ; extra == 'dev'
Requires-Dist: isort ; extra == 'dev'
Provides-Extra: mkl
Requires-Dist: sparse-dot-mkl ; extra == 'mkl'
